MANIFEST.in
README.rst
setup.py
Scrappy.egg-info/PKG-INFO
Scrappy.egg-info/SOURCES.txt
Scrappy.egg-info/dependency_links.txt
Scrappy.egg-info/requires.txt
Scrappy.egg-info/top_level.txt
scrappy/__init__.py
scrappy/core.py
scrappy/docopt.py
scrappy/formatters.py
scrappy/gui.py
scrappy/scrappy.py
scrappy/scrappy.yml
scrappy/titlecase.py
tests/its always sunny i n philadelphia 101.mkv
tests/its always sunny in phil s03e04.avi
tests/its always sunny in philadelphia 1x2.mkv
tests/test.py
tests/test.pyc