Metadata-Version: 1.0
Name: Scrappy
Version: 0.3.0.alpha.4
Summary: Rename video files based on information scraped from thetvdb.com
Home-page: https://github.com/louist87/scrappy
Author: Louis Thibault
Author-email: louist87@gmail.com
License: GPL 3.0
Keywords: TVDB,thetvdb,rename,broadcatching,media
Platform: UNKNOWN
